pdpp/__init__.py
pdpp/automation/__init__.py
pdpp/automation/doit_run.py
pdpp/automation/link_task.py
pdpp/automation/mylinker.py
pdpp/automation/task_creator.py
pdpp/automation/task_enabler.py
pdpp/languages/__init__.py
pdpp/languages/extension_parser.py
pdpp/languages/language_enum.py
pdpp/languages/language_parser.py
pdpp/languages/runners.py
pdpp/main.py
pdpp/questions/__init__.py
pdpp/questions/question_0.py
pdpp/questions/question_1.py
pdpp/questions/question_2.py
pdpp/questions/question_3.py
pdpp/questions/question_4.py
pdpp/questions/question_extant.py
pdpp/styles/__init__.py
pdpp/styles/graph_style.py
pdpp/styles/prompt_style.py
pdpp/tasks/__init__.py
pdpp/tasks/base_task.py
pdpp/tasks/custom_task.py
pdpp/tasks/export_task.py
pdpp/tasks/import_task.py
pdpp/tasks/standard_task.py
pdpp/tasks/sub_task.py
pdpp/templates/__init__.py
pdpp/templates/create_gitignore.py
pdpp/templates/create_in_out_src.py
pdpp/templates/dep_dataclass.py
pdpp/templates/dodo_template.py
pdpp/templates/populate_new_project.py
pdpp/utils/__init__.py
pdpp/utils/directory_test.py
pdpp/utils/execute_at_target.py
pdpp/utils/graph_dependencies.py
pdpp/utils/ignorelist.py
pdpp/utils/immediate_link.py
pdpp/utils/old_graph_dependencies.py
pdpp/utils/rem_slash.py
pdpp/utils/task_directory_test.py
pdpp/utils/yaml_task.py
pdpp-0.5.1.dist-info/LICENSE.txt
pdpp-0.5.1.dist-info/METADATA
pdpp-0.5.1.dist-info/WHEEL
pdpp-0.5.1.dist-info/entry_points.txt
pdpp-0.5.1.dist-info/RECORD
