Metadata-Version: 2.1
Name: pdpp
Version: 0.5.1
Summary: Command line tool for automation, transparency, and reproducibility in data processing projects
Home-page: https://github.com/UWNETLAB/pdpp
License: MIT
Author: Pierson Browne
Author-email: pbrowne88@gmail.com
Requires-Python: >=3.11,<4.0
Classifier: License :: OSI Approved :: MIT License
Classifier: Programming Language :: Python :: 3
Classifier: Programming Language :: Python :: 3.11
Classifier: Programming Language :: Python :: 3.12
Requires-Dist: Click (>=8.1.7,<9.0.0)
Requires-Dist: doit (>=0.36.0,<0.37.0)
Requires-Dist: graphviz (>=0.20.3,<0.21.0)
Requires-Dist: networkx (>=3.3,<4.0)
Requires-Dist: pandas (>=2.2.2,<3.0.0)
Requires-Dist: pydot (>=2.0.0,<3.0.0)
Requires-Dist: pyyaml (>=6.0.1,<7.0.0)
Requires-Dist: questionary (>=2.0.1,<3.0.0)
Requires-Dist: toml (>=0.10.2,<0.11.0)
